src/Makefile
src/pylib.f90
specfunc.py
src/special_functions.f90
src/special_functions.so
specfunc-0.2.0.dist-info/METADATA
specfunc-0.2.0.dist-info/WHEEL
specfunc-0.2.0.dist-info/RECORD
