Metadata-Version: 2.1
Name: specfunc
Version: 0.2.0
Summary: Python wrapper around Fortran codes for special functions.
License: GPLv3-or-above
Author: Alex
Author-email: adrysdale@protonmail.com
Requires-Python: >=3.11,<4.0
Classifier: License :: Other/Proprietary License
Classifier: Programming Language :: Python :: 3
Classifier: Programming Language :: Python :: 3.11
Classifier: Programming Language :: Python :: 3.12
Requires-Dist: numpy (>=1.26.3,<2.0.0)
